LICENSE
MANIFEST.in
README.rst
setup.py
django_modeldict_rc.egg-info/PKG-INFO
django_modeldict_rc.egg-info/SOURCES.txt
django_modeldict_rc.egg-info/dependency_links.txt
django_modeldict_rc.egg-info/not-zip-safe
django_modeldict_rc.egg-info/top_level.txt
modeldict/__init__.py
modeldict/base.py
modeldict/models.py
modeldict/redis.py
tests/__init__.py
tests/modeldict/__init__.py
tests/modeldict/models.py
tests/modeldict/tests.py
tests/modeldict/urls.py