Metadata-Version: 1.1
Name: django-modeldict-rc
Version: 1.3.1
Summary: Stores a model as a dictionary
Home-page: http://github.com/olevinsky/django-modeldict
Author: DISQUS
Author-email: opensource@disqus.com
License: UNKNOWN
Platform: UNKNOWN
Classifier: Framework :: Django
Classifier: Intended Audience :: Developers
Classifier: Intended Audience :: System Administrators
Classifier: Operating System :: OS Independent
Classifier: Topic :: Software Development
